metasyn_disclosure-0.2.0.dist-info/licenses/LICENSE
metasyncontrib/disclosure/__init__.py
metasyncontrib/disclosure/base.py
metasyncontrib/disclosure/categorical.py
metasyncontrib/disclosure/constant.py
metasyncontrib/disclosure/exponential.py
metasyncontrib/disclosure/faker.py
metasyncontrib/disclosure/freetext.py
metasyncontrib/disclosure/na.py
metasyncontrib/disclosure/normal.py
metasyncontrib/disclosure/numerical.py
metasyncontrib/disclosure/poisson.py
metasyncontrib/disclosure/privacy.py
metasyncontrib/disclosure/py.typed
metasyncontrib/disclosure/uniform.py
metasyncontrib/disclosure/uniquekey.py
metasyncontrib/disclosure/utils.py
metasyncontrib/disclosure/visualization.py
metasyn_disclosure-0.2.0.dist-info/METADATA
metasyn_disclosure-0.2.0.dist-info/WHEEL
metasyn_disclosure-0.2.0.dist-info/entry_points.txt
metasyn_disclosure-0.2.0.dist-info/top_level.txt
metasyn_disclosure-0.2.0.dist-info/RECORD
