Metadata-Version: 2.4
Name: metasyn-disclosure
Version: 0.2.0
Summary: Plugin package for metasyn that applies the disclosure control.
Author-email: Raoul Schram <r.d.schram@uu.nl>, Erik-Jan van Kesteren <e.vankesteren1@uu.nl>
License: MIT License
Keywords: metasyn,disclosure control,metadata,open-data,privacy,synthetic-data
Classifier: Programming Language :: Python :: 3
Classifier: Programming Language :: Python :: 3.8
Classifier: Programming Language :: Python :: 3.9
Classifier: Programming Language :: Python :: 3.10
Classifier: Programming Language :: Python :: 3.11
Classifier: Programming Language :: Python :: 3.12
Classifier: Programming Language :: Python :: 3.13
Classifier: Development Status :: 3 - Alpha
Classifier: License :: OSI Approved :: MIT License
Requires-Python: >=3.10
License-File: LICENSE
Requires-Dist: metasyn>=2
Requires-Dist: polars
Requires-Dist: numpy>=1.20; python_version < "3.12"
Requires-Dist: numpy>1.24.4; python_version >= "3.12"
Provides-Extra: dev
Requires-Dist: ruff; extra == "dev"
Requires-Dist: mypy; extra == "dev"
Requires-Dist: pytest; extra == "dev"
Provides-Extra: examples
Requires-Dist: matplotlib; extra == "examples"
Requires-Dist: seaborn; extra == "examples"
Dynamic: license-file
